{
  "NoiseKey": {
    "PublicKeyBase64": "dk3uSG8CqMUKw6Nks2NiD5E5QCk7/XrSXopryDblcEc=",
    "PrivateKeyBase64": "iAw6\u002BITn4O/iFdytYyov9Inyy4HDDi8o4d3r6nczRVE="
  },
  "PairingEphemeralKeyPair": {
    "PublicKeyBase64": "6nWH7bntyf\u002BmcKl8CwQ7g7wEpYWqpozRGSifqFwfujw=",
    "PrivateKeyBase64": "ADXY0rOye9ah6P3xpAmvu8CWJ3Pf91pKA1wCZXXm4XY="
  },
  "SignedIdentityKey": {
    "PublicKeyBase64": "\u002Ba9rFdXc9OGcDhbQQTN\u002BwTuxCMYVr87TN5A4Ma3dCB4=",
    "PrivateKeyBase64": "cNzHRGSFmloiB8j7nzP7subVnaD/Q2qHjkFdoF7Hd1c="
  },
  "AdvSecretKey": "m1ucveBtPweWDGr6dTm6ucrQsupKuzyOwwFpc/Hju/M=",
  "Me": {
    "Id": "13362572629:47@s.whatsapp.net",
    "Lid": "185319970365608:47@lid",
    "Name": "Skippy Asyermuni"
  },
  "Account": "ChIIzpHWxwwQycGfzgYYASAAKAASIPo1HspWXLLiEG1F1\u002Br3P82L6UEewIfR6LDSWYRRG2JMGkCdz/7vtnoDXpxwnwn\u002BWuF\u002BWAJdBRkWFg90i3DmYkBqncDJkbo16/el\u002BaCxOzwDL4sklD/ZH6KbFOqGj7hhxS4JIkA03vOVE1XxJhXaArclv7FxPVNkCjvRRxfMfIy2Y21FvtDR820P0zYg2xpUWqV9mUZz6BJ2MsuMea4Gcb45JpII",
  "SignalIdentities": [
    {
      "Identifier": "185319970365608:47@lid",
      "IdentifierKey": "Bfo1HspWXLLiEG1F1\u002Br3P82L6UEewIfR6LDSWYRRG2JM"
    }
  ],
  "MyAppStateKeyId": "AAAAAA4r",
  "FirstUnuploadedPreKeyId": 813,
  "NextPreKeyId": 813,
  "LastAccountSyncTimestamp": 1777140372,
  "Platform": "iphone",
  "ProcessedHistoryMessages": [
    {
      "Id": "3EB06B126EEE10F9CCC812",
      "RemoteJid": "87201358569541@lid",
      "MessageTimestamp": 1774701213
    },
    {
      "Id": "3AE456E89E9C0DC7F11A",
      "RemoteJid": "87201358569541@lid",
      "MessageTimestamp": 1774701213
    },
    {
      "Id": "AC4039C8F5BFF8E428ADE0BF7762DA14",
      "RemoteJid": "44208299757676@lid",
      "MessageTimestamp": 1774466886
    },
    {
      "Id": "409071258500507-1",
      "RemoteJid": "0@s.whatsapp.net",
      "MessageTimestamp": 1774222211
    },
    {
      "Id": "3A6E6B745AB3C5FB81D1",
      "RemoteJid": "241553272475724@lid",
      "MessageTimestamp": 1773531378
    },
    {
      "Id": "3A26A745586CE4122CE7",
      "RemoteJid": "120363395177329324@g.us",
      "MessageTimestamp": 1773416708
    },
    {
      "Id": "ACB8B92F9440B9447B82229F36DE8790",
      "RemoteJid": "120363410460716063@g.us",
      "MessageTimestamp": 1772834057
    }
  ],
  "AccountSyncCounter": 1,
  "AccountSettings": {
    "UnarchiveChats": false,
    "DefaultDisappearingMode": null
  },
  "Registered": false,
  "PairingCode": "9JXDF6B8",
  "LastPropHash": null,
  "RoutingInfo": "CAUIAggS",
  "AdditionalData": null,
  "SignedPreKey": {
    "KeyId": 1,
    "KeyPair": {
      "PublicKeyBase64": "u8C9bkfFRBON5BepoWeT2F9P4kZQv6O4tZNMm3xCuwc=",
      "PrivateKeyBase64": "gNCmo1a/B87RBME8ARorFXDyc5iflq9DLIoKUfQh7Hg="
    },
    "SignatureBase64": "KM0QBGOwCHdrVEF8176NCdsaoTjSAIg0QnFeQPu1OTg\u002BsYcHMArnac4F1euhzBj1RfS/Nkj4EVHLU8M6a/FBDQ==",
    "TimestampSeconds": 1774706881
  },
  "RegistrationId": 14231,
  "TcToken": null,
  "TcTokenKey": null,
  "TcTokenTimestamp": null,
  "LidMapping": {
    "87201358569541@lid": "13366930850@s.whatsapp.net",
    "185319970365608@lid": "13362572629@s.whatsapp.net",
    "27818654232641@lid": "19108559096@s.whatsapp.net"
  },
  "AppStateCollectionVersions": {}
}